README.md
setup.py
tmatplot/__init__.py
tmatplot/basics.py
tmatplot/styles.py
tmatplot/utils.py
tmatplot/waves.py
tmatplot.egg-info/PKG-INFO
tmatplot.egg-info/SOURCES.txt
tmatplot.egg-info/dependency_links.txt
tmatplot.egg-info/requires.txt
tmatplot.egg-info/top_level.txt