Metadata-Version: 1.1
Name: tmatplot
Version: 0.1.5
Summary: high level interface based on matplotlib for personal use
Home-page: https://github.com/taehoonlee/tmatplot
Author: Taehoon Lee
Author-email: me@taehoonlee.com
License: MIT
Download-URL: https://github.com/taehoonlee/tmatplot/tarball/master
Platform: UNKNOWN
